{
  "full_history": [
    {
      "generation": 0,
      "best_fitness": 430.36443772066957,
      "avg_fitness": 430.36443772066957,
      "diversity_metrics": {
        "population_diversity": 0.40889337387316127,
        "mutation_range": 0.8
      }
    },
    {
      "generation": 1,
      "best_fitness": 430.36443772066957,
      "avg_fitness": 430.36443772066957,
      "diversity_metrics": {
        "population_diversity": 0.3707453207636566,
        "mutation_range": 0.7933333333333334
      }
    },
    {
      "generation": 2,
      "best_fitness": 430.36443772066957,
      "avg_fitness": 430.3644377206695,
      "diversity_metrics": {
        "population_diversity": 0.33521561616996565,
        "mutation_range": 0.7866666666666666
      }
    },
    {
      "generation": 3,
      "best_fitness": 371.95530809399384,
      "avg_fitness": 415.7621553140006,
      "diversity_metrics": {
        "population_diversity": 0.34583629414656203,
        "mutation_range": 0.78
      }
    },
    {
      "generation": 4,
      "best_fitness": 371.95530809399384,
      "avg_fitness": 426.88174863770354,
      "diversity_metrics": {
        "population_diversity": 0.33563159867889597,
        "mutation_range": 0.7733333333333334
      }
    },
    {
      "generation": 5,
      "best_fitness": 371.95530809399384,
      "avg_fitness": 418.78758650297283,
      "diversity_metrics": {
        "population_diversity": 0.3205116637903075,
        "mutation_range": 0.7666666666666667
      }
    },
    {
      "generation": 6,
      "best_fitness": 364.98287861862593,
      "avg_fitness": 411.10119966235186,
      "diversity_metrics": {
        "population_diversity": 0.3102033733599714,
        "mutation_range": 0.76
      }
    },
    {
      "generation": 7,
      "best_fitness": 364.98287861862593,
      "avg_fitness": 405.33640953188615,
      "diversity_metrics": {
        "population_diversity": 0.3160653424555773,
        "mutation_range": 0.7533333333333334
      }
    },
    {
      "generation": 8,
      "best_fitness": 364.98287861862593,
      "avg_fitness": 411.97476488746724,
      "diversity_metrics": {
        "population_diversity": 0.31860809362709125,
        "mutation_range": 0.7466666666666667
      }
    },
    {
      "generation": 9,
      "best_fitness": 364.98287861862593,
      "avg_fitness": 417.2854491719321,
      "diversity_metrics": {
        "population_diversity": 0.30355446058957686,
        "mutation_range": 0.7400000000000001
      }
    },
    {
      "generation": 10,
      "best_fitness": 364.98287861862593,
      "avg_fitness": 422.97626483716044,
      "diversity_metrics": {
        "population_diversity": 0.31369468897542524,
        "mutation_range": 0.7333333333333334
      }
    },
    {
      "generation": 11,
      "best_fitness": 364.98287861862593,
      "avg_fitness": 428.36948008524854,
      "diversity_metrics": {
        "population_diversity": 0.3304544223440596,
        "mutation_range": 0.7266666666666667
      }
    },
    {
      "generation": 12,
      "best_fitness": 364.98287861862593,
      "avg_fitness": 428.86617978703447,
      "diversity_metrics": {
        "population_diversity": 0.3159190261296711,
        "mutation_range": 0.7200000000000001
      }
    },
    {
      "generation": 13,
      "best_fitness": 364.98287861862593,
      "avg_fitness": 429.29192238856524,
      "diversity_metrics": {
        "population_diversity": 0.34006048738745664,
        "mutation_range": 0.7133333333333334
      }
    },
    {
      "generation": 14,
      "best_fitness": 364.98287861862593,
      "avg_fitness": 429.66089930989193,
      "diversity_metrics": {
        "population_diversity": 0.30545836819926014,
        "mutation_range": 0.7066666666666667
      }
    },
    {
      "generation": 15,
      "best_fitness": 364.98287861862593,
      "avg_fitness": 429.98375411605275,
      "diversity_metrics": {
        "population_diversity": 0.3191686255851808,
        "mutation_range": 0.7000000000000001
      }
    },
    {
      "generation": 16,
      "best_fitness": 364.98287861862593,
      "avg_fitness": 430.26862600384175,
      "diversity_metrics": {
        "population_diversity": 0.29910165325415894,
        "mutation_range": 0.6933333333333334
      }
    },
    {
      "generation": 17,
      "best_fitness": 364.98287861862593,
      "avg_fitness": 430.5218454596542,
      "diversity_metrics": {
        "population_diversity": 0.29761128588915076,
        "mutation_range": 0.6866666666666668
      }
    },
    {
      "generation": 18,
      "best_fitness": 364.98287861862593,
      "avg_fitness": 430.74841023590744,
      "diversity_metrics": {
        "population_diversity": 0.28658303610264785,
        "mutation_range": 0.68
      }
    },
    {
      "generation": 19,
      "best_fitness": 364.98287861862593,
      "avg_fitness": 430.9523185345353,
      "diversity_metrics": {
        "population_diversity": 0.2627460181669314,
        "mutation_range": 0.6733333333333333
      }
    },
    {
      "generation": 20,
      "best_fitness": 364.98287861862593,
      "avg_fitness": 429.97692795328743,
      "diversity_metrics": {
        "population_diversity": 0.2641539204127947,
        "mutation_range": 0.6666666666666667
      }
    },
    {
      "generation": 21,
      "best_fitness": 364.98287861862593,
      "avg_fitness": 429.0902092430621,
      "diversity_metrics": {
        "population_diversity": 0.24811915474893279,
        "mutation_range": 0.66
      }
    },
    {
      "generation": 22,
      "best_fitness": 364.98287861862593,
      "avg_fitness": 428.28059650763896,
      "diversity_metrics": {
        "population_diversity": 0.27464985313427925,
        "mutation_range": 0.6533333333333333
      }
    },
    {
      "generation": 23,
      "best_fitness": 364.98287861862593,
      "avg_fitness": 427.5384515001677,
      "diversity_metrics": {
        "population_diversity": 0.28603583321666615,
        "mutation_range": 0.6466666666666667
      }
    },
    {
      "generation": 24,
      "best_fitness": 364.98287861862593,
      "avg_fitness": 426.8556780932942,
      "diversity_metrics": {
        "population_diversity": 0.2754899656155749,
        "mutation_range": 0.6400000000000001
      }
    },
    {
      "generation": 25,
      "best_fitness": 364.98287861862593,
      "avg_fitness": 427.4013183325915,
      "diversity_metrics": {
        "population_diversity": 0.29785426667623466,
        "mutation_range": 0.6333333333333333
      }
    },
    {
      "generation": 26,
      "best_fitness": 364.98287861862593,
      "avg_fitness": 427.16986469496067,
      "diversity_metrics": {
        "population_diversity": 0.3066000699345921,
        "mutation_range": 0.6266666666666667
      }
    },
    {
      "generation": 27,
      "best_fitness": 364.98287861862593,
      "avg_fitness": 426.9549434600177,
      "diversity_metrics": {
        "population_diversity": 0.30473606263656133,
        "mutation_range": 0.6200000000000001
      }
    },
    {
      "generation": 28,
      "best_fitness": 364.98287861862593,
      "avg_fitness": 426.7548443792088,
      "diversity_metrics": {
        "population_diversity": 0.3077379166015304,
        "mutation_range": 0.6133333333333333
      }
    },
    {
      "generation": 29,
      "best_fitness": 364.98287861862593,
      "avg_fitness": 425.54344670448336,
      "diversity_metrics": {
        "population_diversity": 0.27495147498319106,
        "mutation_range": 0.6066666666666667
      }
    },
    {
      "generation": 30,
      "best_fitness": 364.98287861862593,
      "avg_fitness": 424.4102037184498,
      "diversity_metrics": {
        "population_diversity": 0.25414782180317064,
        "mutation_range": 0.6000000000000001
      }
    },
    {
      "generation": 31,
      "best_fitness": 364.98287861862593,
      "avg_fitness": 423.34778841904335,
      "diversity_metrics": {
        "population_diversity": 0.2631479990350703,
        "mutation_range": 0.5933333333333334
      }
    },
    {
      "generation": 32,
      "best_fitness": 364.98287861862593,
      "avg_fitness": 424.88020869280354,
      "diversity_metrics": {
        "population_diversity": 0.29670503650001334,
        "mutation_range": 0.5866666666666668
      }
    },
    {
      "generation": 33,
      "best_fitness": 364.98287861862593,
      "avg_fitness": 425.5567673411963,
      "diversity_metrics": {
        "population_diversity": 0.2839514097811987,
        "mutation_range": 0.58
      }
    },
    {
      "generation": 34,
      "best_fitness": 364.98287861862593,
      "avg_fitness": 426.1946654953951,
      "diversity_metrics": {
        "population_diversity": 0.2824604903236905,
        "mutation_range": 0.5733333333333334
      }
    },
    {
      "generation": 35,
      "best_fitness": 364.98287861862593,
      "avg_fitness": 426.79712486324956,
      "diversity_metrics": {
        "population_diversity": 0.2775975146660219,
        "mutation_range": 0.5666666666666667
      }
    },
    {
      "generation": 36,
      "best_fitness": 364.98287861862593,
      "avg_fitness": 427.36701885986867,
      "diversity_metrics": {
        "population_diversity": 0.3156880033280756,
        "mutation_range": 0.5599999999999999
      }
    },
    {
      "generation": 37,
      "best_fitness": 364.98287861862593,
      "avg_fitness": 427.9069184356131,
      "diversity_metrics": {
        "population_diversity": 0.2795431145982187,
        "mutation_range": 0.5533333333333333
      }
    },
    {
      "generation": 38,
      "best_fitness": 364.98287861862593,
      "avg_fitness": 428.17024815600513,
      "diversity_metrics": {
        "population_diversity": 0.26945983883436697,
        "mutation_range": 0.5466666666666667
      }
    },
    {
      "generation": 39,
      "best_fitness": 364.98287861862593,
      "avg_fitness": 428.4204113903776,
      "diversity_metrics": {
        "population_diversity": 0.2592568405267503,
        "mutation_range": 0.54
      }
    },
    {
      "generation": 40,
      "best_fitness": 364.98287861862593,
      "avg_fitness": 428.6583715401465,
      "diversity_metrics": {
        "population_diversity": 0.24894865212768666,
        "mutation_range": 0.5333333333333334
      }
    },
    {
      "generation": 41,
      "best_fitness": 364.98287861862593,
      "avg_fitness": 428.2201939449698,
      "diversity_metrics": {
        "population_diversity": 0.25121541309052775,
        "mutation_range": 0.5266666666666667
      }
    },
    {
      "generation": 42,
      "best_fitness": 364.98287861862593,
      "avg_fitness": 427.8023967030571,
      "diversity_metrics": {
        "population_diversity": 0.2739331946488734,
        "mutation_range": 0.52
      }
    },
    {
      "generation": 43,
      "best_fitness": 364.98287861862593,
      "avg_fitness": 427.64274296563167,
      "diversity_metrics": {
        "population_diversity": 0.2616917214489716,
        "mutation_range": 0.5133333333333333
      }
    },
    {
      "generation": 44,
      "best_fitness": 364.98287861862593,
      "avg_fitness": 427.43858377039885,
      "diversity_metrics": {
        "population_diversity": 0.3313902003141434,
        "mutation_range": 0.5066666666666667
      }
    },
    {
      "generation": 45,
      "best_fitness": 364.98287861862593,
      "avg_fitness": 427.06997831632185,
      "diversity_metrics": {
        "population_diversity": 0.3054458507573997,
        "mutation_range": 0.5
      }
    },
    {
      "generation": 46,
      "best_fitness": 364.98287861862593,
      "avg_fitness": 426.7170582007163,
      "diversity_metrics": {
        "population_diversity": 0.31051816263082876,
        "mutation_range": 0.4933333333333334
      }
    },
    {
      "generation": 47,
      "best_fitness": 364.98287861862593,
      "avg_fitness": 426.04871762945095,
      "diversity_metrics": {
        "population_diversity": 0.28702807525109114,
        "mutation_range": 0.48666666666666675
      }
    },
    {
      "generation": 48,
      "best_fitness": 364.98287861862593,
      "avg_fitness": 425.4076562651761,
      "diversity_metrics": {
        "population_diversity": 0.3056913236650616,
        "mutation_range": 0.48
      }
    },
    {
      "generation": 49,
      "best_fitness": 364.98287861862593,
      "avg_fitness": 424.7922373554723,
      "diversity_metrics": {
        "population_diversity": 0.24959389802160284,
        "mutation_range": 0.4733333333333334
      }
    },
    {
      "generation": 50,
      "best_fitness": 364.98287861862593,
      "avg_fitness": 424.20095252065886,
      "diversity_metrics": {
        "population_diversity": 0.2784315413184759,
        "mutation_range": 0.4666666666666666
      }
    },
    {
      "generation": 51,
      "best_fitness": 364.98287861862593,
      "avg_fitness": 423.6324094102613,
      "diversity_metrics": {
        "population_diversity": 0.26167993781345567,
        "mutation_range": 0.45999999999999996
      }
    },
    {
      "generation": 52,
      "best_fitness": 364.98287861862593,
      "avg_fitness": 423.08532075685986,
      "diversity_metrics": {
        "population_diversity": 0.24968640769373818,
        "mutation_range": 0.45333333333333337
      }
    },
    {
      "generation": 53,
      "best_fitness": 364.98287861862593,
      "avg_fitness": 422.558494646177,
      "diversity_metrics": {
        "population_diversity": 0.24797390612957568,
        "mutation_range": 0.4466666666666667
      }
    },
    {
      "generation": 54,
      "best_fitness": 364.98287861862593,
      "avg_fitness": 422.05082584860986,
      "diversity_metrics": {
        "population_diversity": 0.23312651940808662,
        "mutation_range": 0.44000000000000006
      }
    },
    {
      "generation": 55,
      "best_fitness": 364.98287861862593,
      "avg_fitness": 421.56128807952706,
      "diversity_metrics": {
        "population_diversity": 0.24722449492553542,
        "mutation_range": 0.4333333333333334
      }
    },
    {
      "generation": 56,
      "best_fitness": 364.98287861862593,
      "avg_fitness": 421.08892707427196,
      "diversity_metrics": {
        "population_diversity": 0.24975403720842568,
        "mutation_range": 0.4266666666666667
      }
    },
    {
      "generation": 57,
      "best_fitness": 364.98287861862593,
      "avg_fitness": 420.6328543795429,
      "diversity_metrics": {
        "population_diversity": 0.24800266450099834,
        "mutation_range": 0.42000000000000004
      }
    },
    {
      "generation": 58,
      "best_fitness": 364.98287861862593,
      "avg_fitness": 420.19224177616053,
      "diversity_metrics": {
        "population_diversity": 0.24154596900558842,
        "mutation_range": 0.41333333333333333
      }
    },
    {
      "generation": 59,
      "best_fitness": 364.98287861862593,
      "avg_fitness": 419.7663162595576,
      "diversity_metrics": {
        "population_diversity": 0.2643575165056387,
        "mutation_range": 0.4066666666666667
      }
    },
    {
      "generation": 60,
      "best_fitness": 364.98287861862593,
      "avg_fitness": 419.35435551399087,
      "diversity_metrics": {
        "population_diversity": 0.25399758701531505,
        "mutation_range": 0.4
      }
    },
    {
      "generation": 61,
      "best_fitness": 364.98287861862593,
      "avg_fitness": 418.9556838247327,
      "diversity_metrics": {
        "population_diversity": 0.22914272297637897,
        "mutation_range": 0.39333333333333337
      }
    },
    {
      "generation": 62,
      "best_fitness": 364.98287861862593,
      "avg_fitness": 418.93628240786785,
      "diversity_metrics": {
        "population_diversity": 0.295012761290476,
        "mutation_range": 0.38666666666666666
      }
    },
    {
      "generation": 63,
      "best_fitness": 364.98287861862593,
      "avg_fitness": 418.9174872852799,
      "diversity_metrics": {
        "population_diversity": 0.31647265813996683,
        "mutation_range": 0.38
      }
    },
    {
      "generation": 64,
      "best_fitness": 364.98287861862593,
      "avg_fitness": 418.8992704741563,
      "diversity_metrics": {
        "population_diversity": 0.2512675047377351,
        "mutation_range": 0.37333333333333335
      }
    },
    {
      "generation": 65,
      "best_fitness": 364.98287861862593,
      "avg_fitness": 418.83978670400006,
      "diversity_metrics": {
        "population_diversity": 0.25995383346250056,
        "mutation_range": 0.3666666666666667
      }
    },
    {
      "generation": 66,
      "best_fitness": 364.98287861862593,
      "avg_fitness": 418.2423955903782,
      "diversity_metrics": {
        "population_diversity": 0.2679665931088431,
        "mutation_range": 0.36
      }
    },
    {
      "generation": 67,
      "best_fitness": 364.98287861862593,
      "avg_fitness": 417.66257480362754,
      "diversity_metrics": {
        "population_diversity": 0.26397191311974105,
        "mutation_range": 0.35333333333333333
      }
    },
    {
      "generation": 68,
      "best_fitness": 364.98287861862593,
      "avg_fitness": 417.09956041649286,
      "diversity_metrics": {
        "population_diversity": 0.27137817199676073,
        "mutation_range": 0.3466666666666667
      }
    },
    {
      "generation": 69,
      "best_fitness": 364.98287861862593,
      "avg_fitness": 416.5526321547049,
      "diversity_metrics": {
        "population_diversity": 0.2733843554771288,
        "mutation_range": 0.3400000000000001
      }
    },
    {
      "generation": 70,
      "best_fitness": 364.98287861862593,
      "avg_fitness": 416.0211103228264,
      "diversity_metrics": {
        "population_diversity": 0.3058074874038026,
        "mutation_range": 0.3333333333333333
      }
    },
    {
      "generation": 71,
      "best_fitness": 364.98287861862593,
      "avg_fitness": 415.50435298627804,
      "diversity_metrics": {
        "population_diversity": 0.295984346899523,
        "mutation_range": 0.32666666666666666
      }
    },
    {
      "generation": 72,
      "best_fitness": 364.98287861862593,
      "avg_fitness": 415.0017533849774,
      "diversity_metrics": {
        "population_diversity": 0.29367365055370104,
        "mutation_range": 0.32000000000000006
      }
    },
    {
      "generation": 73,
      "best_fitness": 364.98287861862593,
      "avg_fitness": 414.51273755668495,
      "diversity_metrics": {
        "population_diversity": 0.2884232068318432,
        "mutation_range": 0.3133333333333334
      }
    },
    {
      "generation": 74,
      "best_fitness": 364.98287861862593,
      "avg_fitness": 414.03676215048023,
      "diversity_metrics": {
        "population_diversity": 0.31998818313072075,
        "mutation_range": 0.30666666666666664
      }
    },
    {
      "generation": 75,
      "best_fitness": 364.98287861862593,
      "avg_fitness": 413.57331241285993,
      "diversity_metrics": {
        "population_diversity": 0.30659363619221064,
        "mutation_range": 0.30000000000000004
      }
    },
    {
      "generation": 76,
      "best_fitness": 364.98287861862593,
      "avg_fitness": 413.1219003307622,
      "diversity_metrics": {
        "population_diversity": 0.32211300832056194,
        "mutation_range": 0.2933333333333334
      }
    },
    {
      "generation": 77,
      "best_fitness": 364.98287861862593,
      "avg_fitness": 412.68206291743616,
      "diversity_metrics": {
        "population_diversity": 0.31542909138672864,
        "mutation_range": 0.2866666666666666
      }
    },
    {
      "generation": 78,
      "best_fitness": 364.98287861862593,
      "avg_fitness": 412.25336062849817,
      "diversity_metrics": {
        "population_diversity": 0.30413659951703437,
        "mutation_range": 0.27999999999999997
      }
    },
    {
      "generation": 79,
      "best_fitness": 364.98287861862593,
      "avg_fitness": 411.8353758967837,
      "diversity_metrics": {
        "population_diversity": 0.31921707122166143,
        "mutation_range": 0.2733333333333334
      }
    },
    {
      "generation": 80,
      "best_fitness": 364.98287861862593,
      "avg_fitness": 411.42771177572877,
      "diversity_metrics": {
        "population_diversity": 0.3015060359421807,
        "mutation_range": 0.2666666666666667
      }
    },
    {
      "generation": 81,
      "best_fitness": 364.98287861862593,
      "avg_fitness": 411.02999068201666,
      "diversity_metrics": {
        "population_diversity": 0.32935791169109335,
        "mutation_range": 0.25999999999999995
      }
    },
    {
      "generation": 82,
      "best_fitness": 361.82950593353314,
      "avg_fitness": 410.43721375733617,
      "diversity_metrics": {
        "population_diversity": 0.3143418546138253,
        "mutation_range": 0.25333333333333335
      }
    },
    {
      "generation": 83,
      "best_fitness": 347.8547296309213,
      "avg_fitness": 409.6921841844026,
      "diversity_metrics": {
        "population_diversity": 0.3129821847102337,
        "mutation_range": 0.2466666666666667
      }
    },
    {
      "generation": 84,
      "best_fitness": 347.8547296309213,
      "avg_fitness": 408.9646847190675,
      "diversity_metrics": {
        "population_diversity": 0.31438074915842046,
        "mutation_range": 0.24000000000000005
      }
    },
    {
      "generation": 85,
      "best_fitness": 347.8547296309213,
      "avg_fitness": 408.2541038459495,
      "diversity_metrics": {
        "population_diversity": 0.3006746472716409,
        "mutation_range": 0.2333333333333333
      }
    },
    {
      "generation": 86,
      "best_fitness": 347.8547296309213,
      "avg_fitness": 407.559858165317,
      "diversity_metrics": {
        "population_diversity": 0.3176868574952755,
        "mutation_range": 0.22666666666666668
      }
    },
    {
      "generation": 87,
      "best_fitness": 347.8547296309213,
      "avg_fitness": 406.88139079560807,
      "diversity_metrics": {
        "population_diversity": 0.29715693219401834,
        "mutation_range": 0.22000000000000003
      }
    },
    {
      "generation": 88,
      "best_fitness": 347.8547296309213,
      "avg_fitness": 406.21816988364526,
      "diversity_metrics": {
        "population_diversity": 0.28837513609455295,
        "mutation_range": 0.21333333333333337
      }
    },
    {
      "generation": 89,
      "best_fitness": 346.3354718591402,
      "avg_fitness": 405.55280657226194,
      "diversity_metrics": {
        "population_diversity": 0.279280994119212,
        "mutation_range": 0.20666666666666667
      }
    },
    {
      "generation": 90,
      "best_fitness": 346.3354718591402,
      "avg_fitness": 404.9020666303595,
      "diversity_metrics": {
        "population_diversity": 0.2972898269102042,
        "mutation_range": 0.2
      }
    },
    {
      "generation": 91,
      "best_fitness": 346.3354718591402,
      "avg_fitness": 405.08337130978185,
      "diversity_metrics": {
        "population_diversity": 0.3162786846333505,
        "mutation_range": 0.19333333333333336
      }
    },
    {
      "generation": 92,
      "best_fitness": 346.3354718591402,
      "avg_fitness": 405.2607769638403,
      "diversity_metrics": {
        "population_diversity": 0.34062432551395716,
        "mutation_range": 0.18666666666666665
      }
    },
    {
      "generation": 93,
      "best_fitness": 346.3354718591402,
      "avg_fitness": 405.4344080295145,
      "diversity_metrics": {
        "population_diversity": 0.3060293587889734,
        "mutation_range": 0.18
      }
    },
    {
      "generation": 94,
      "best_fitness": 346.3354718591402,
      "avg_fitness": 405.6043837043324,
      "diversity_metrics": {
        "population_diversity": 0.2913564835153545,
        "mutation_range": 0.17333333333333334
      }
    },
    {
      "generation": 95,
      "best_fitness": 346.3354718591402,
      "avg_fitness": 405.77081821925805,
      "diversity_metrics": {
        "population_diversity": 0.311415461779249,
        "mutation_range": 0.1666666666666667
      }
    },
    {
      "generation": 96,
      "best_fitness": 346.3354718591402,
      "avg_fitness": 405.93382109470093,
      "diversity_metrics": {
        "population_diversity": 0.29678273690413143,
        "mutation_range": 0.15999999999999998
      }
    },
    {
      "generation": 97,
      "best_fitness": 346.3354718591402,
      "avg_fitness": 406.09349738084904,
      "diversity_metrics": {
        "population_diversity": 0.2962687196502795,
        "mutation_range": 0.15333333333333332
      }
    },
    {
      "generation": 98,
      "best_fitness": 346.3354718591402,
      "avg_fitness": 405.580037358539,
      "diversity_metrics": {
        "population_diversity": 0.2917049050677001,
        "mutation_range": 0.1466666666666667
      }
    },
    {
      "generation": 99,
      "best_fitness": 346.3354718591402,
      "avg_fitness": 405.07684653667513,
      "diversity_metrics": {
        "population_diversity": 0.2686386664224371,
        "mutation_range": 0.14000000000000004
      }
    },
    {
      "generation": 100,
      "best_fitness": 346.3354718591402,
      "avg_fitness": 404.32581171119006,
      "diversity_metrics": {
        "population_diversity": 0.30868985486499856,
        "mutation_range": 0.1333333333333333
      }
    },
    {
      "generation": 101,
      "best_fitness": 346.3354718591402,
      "avg_fitness": 404.7857444317768,
      "diversity_metrics": {
        "population_diversity": 0.29714466387466837,
        "mutation_range": 0.12666666666666668
      }
    },
    {
      "generation": 102,
      "best_fitness": 346.3354718591402,
      "avg_fitness": 404.4575521257803,
      "diversity_metrics": {
        "population_diversity": 0.297405906236102,
        "mutation_range": 0.12000000000000002
      }
    },
    {
      "generation": 103,
      "best_fitness": 346.3354718591402,
      "avg_fitness": 404.71345111605046,
      "diversity_metrics": {
        "population_diversity": 0.3181401574931038,
        "mutation_range": 0.11333333333333338
      }
    },
    {
      "generation": 104,
      "best_fitness": 346.3354718591402,
      "avg_fitness": 403.97530196793554,
      "diversity_metrics": {
        "population_diversity": 0.30066286142363374,
        "mutation_range": 0.10666666666666665
      }
    },
    {
      "generation": 105,
      "best_fitness": 346.3354718591402,
      "avg_fitness": 404.1675862808525,
      "diversity_metrics": {
        "population_diversity": 0.3059557187764013,
        "mutation_range": 0.1
      }
    },
    {
      "generation": 106,
      "best_fitness": 346.3354718591402,
      "avg_fitness": 405.0470969948815,
      "diversity_metrics": {
        "population_diversity": 0.3134510094191264,
        "mutation_range": 0.09333333333333337
      }
    },
    {
      "generation": 107,
      "best_fitness": 346.3354718591402,
      "avg_fitness": 405.9266077089106,
      "diversity_metrics": {
        "population_diversity": 0.2913161619345142,
        "mutation_range": 0.08666666666666663
      }
    },
    {
      "generation": 108,
      "best_fitness": 346.3354718591402,
      "avg_fitness": 405.80513113180467,
      "diversity_metrics": {
        "population_diversity": 0.2746098039796289,
        "mutation_range": 0.07999999999999999
      }
    },
    {
      "generation": 109,
      "best_fitness": 346.3354718591402,
      "avg_fitness": 405.52182039073523,
      "diversity_metrics": {
        "population_diversity": 0.2825524586974003,
        "mutation_range": 0.07333333333333335
      }
    },
    {
      "generation": 110,
      "best_fitness": 346.3354718591402,
      "avg_fitness": 405.08328370557575,
      "diversity_metrics": {
        "population_diversity": 0.27954616989565245,
        "mutation_range": 0.0666666666666667
      }
    },
    {
      "generation": 111,
      "best_fitness": 346.3354718591402,
      "avg_fitness": 404.5666427571686,
      "diversity_metrics": {
        "population_diversity": 0.289107367206612,
        "mutation_range": 0.05999999999999997
      }
    },
    {
      "generation": 112,
      "best_fitness": 346.3354718591402,
      "avg_fitness": 404.578684524819,
      "diversity_metrics": {
        "population_diversity": 0.29473782423627165,
        "mutation_range": 0.05333333333333332
      }
    },
    {
      "generation": 113,
      "best_fitness": 346.3354718591402,
      "avg_fitness": 404.59072629246936,
      "diversity_metrics": {
        "population_diversity": 0.26553349294924167,
        "mutation_range": 0.04666666666666668
      }
    },
    {
      "generation": 114,
      "best_fitness": 346.3354718591402,
      "avg_fitness": 404.6027680601196,
      "diversity_metrics": {
        "population_diversity": 0.27844014120452293,
        "mutation_range": 0.040000000000000036
      }
    },
    {
      "generation": 115,
      "best_fitness": 346.3354718591402,
      "avg_fitness": 404.1506452360552,
      "diversity_metrics": {
        "population_diversity": 0.28198339365844544,
        "mutation_range": 0.033333333333333305
      }
    },
    {
      "generation": 116,
      "best_fitness": 346.3354718591402,
      "avg_fitness": 403.6985224119908,
      "diversity_metrics": {
        "population_diversity": 0.27913737272533945,
        "mutation_range": 0.02666666666666666
      }
    },
    {
      "generation": 117,
      "best_fitness": 346.3354718591402,
      "avg_fitness": 403.2463995879263,
      "diversity_metrics": {
        "population_diversity": 0.2739648610815786,
        "mutation_range": 0.020000000000000018
      }
    },
    {
      "generation": 118,
      "best_fitness": 346.3354718591402,
      "avg_fitness": 402.79427676386183,
      "diversity_metrics": {
        "population_diversity": 0.268256025732102,
        "mutation_range": 0.013333333333333376
      }
    },
    {
      "generation": 119,
      "best_fitness": 346.3354718591402,
      "avg_fitness": 402.56506726404683,
      "diversity_metrics": {
        "population_diversity": 0.28822718453204593,
        "mutation_range": 0.006666666666666644
      }
    }
  ],
  "feature_summary": {
    "improvement_points": [
      {
        "generation": 3,
        "improvement": 58.409129626675735,
        "fitness": 371.95530809399384
      },
      {
        "generation": 6,
        "improvement": 6.972429475367903,
        "fitness": 364.98287861862593
      },
      {
        "generation": 83,
        "improvement": 13.974776302611815,
        "fitness": 347.8547296309213
      }
    ],
    "plateau_periods": [
      {
        "start": 6,
        "end": 15,
        "fitness_variance": 0.0
      },
      {
        "start": 27,
        "end": 36,
        "fitness_variance": 0.0
      },
      {
        "start": 48,
        "end": 57,
        "fitness_variance": 0.0
      },
      {
        "start": 69,
        "end": 78,
        "fitness_variance": 0.0
      },
      {
        "start": 90,
        "end": 99,
        "fitness_variance": 3.2311742677852644e-27
      }
    ],
    "diversity_trends": [],
    "convergence_events": []
  },
  "elite_archive_count": 50,
  "diversity_pool_count": 50
}